cli.py
image.py
terminal_img-0.0.3.dist-info/LICENSE
terminal_img-0.0.3.dist-info/METADATA
terminal_img-0.0.3.dist-info/WHEEL
terminal_img-0.0.3.dist-info/entry_points.txt
terminal_img-0.0.3.dist-info/top_level.txt
terminal_img-0.0.3.dist-info/RECORD
