Metadata-Version: 2.1
Name: terminal-img
Version: 0.0.3
Summary: Display images in the terminal
Home-page: https://github.com/pranavbaburaj/img
Author: Pranav Baburaj
Author-email: i.am.pranav.baburaj@gmail.com
License: MIT
Platform: UNKNOWN
Classifier: Development Status :: 5 - Production/Stable
Classifier: Programming Language :: Python :: 3
Classifier: Intended Audience :: Developers
Classifier: License :: OSI Approved :: MIT License
Classifier: Topic :: Software Development :: Libraries
Classifier: Topic :: Utilities
Requires-Python: >=3.6
License-File: LICENSE
Requires-Dist: pillow
Requires-Dist: requests
